textual_textarea/__init__.py
textual_textarea/__main__.py
textual_textarea/autocomplete.py
textual_textarea/cancellable_input.py
textual_textarea/colors.py
textual_textarea/comments.py
textual_textarea/containers.py
textual_textarea/error_modal.py
textual_textarea/find_input.py
textual_textarea/goto_input.py
textual_textarea/messages.py
textual_textarea/path_input.py
textual_textarea/py.typed
textual_textarea/text_editor.py
textual_textarea-0.17.2.dist-info/METADATA
textual_textarea-0.17.2.dist-info/WHEEL
textual_textarea-0.17.2.dist-info/licenses/LICENSE
textual_textarea-0.17.2.dist-info/RECORD
