Metadata-Version: 2.4
Name: textual-textarea
Version: 0.17.2
Summary: A text area (multi-line input) with syntax highlighting for Textual
Project-URL: Homepage, https://github.com/tconbeer/textual-textarea
Project-URL: Repository, https://github.com/tconbeer/textual-textarea
Author-email: Ted Conbeer <tconbeer@users.noreply.github.com>
License-Expression: MIT
License-File: LICENSE
Requires-Python: <3.15,>=3.10
Requires-Dist: pyperclip<2,>=1.9.0
Requires-Dist: textual[syntax]<7,>=6.4.0
